brushit/__init__.py
brushit/cli.py
brushit/controller.py
brushit/duster.py
brushit/git.py
brushit-0.3.0.dist-info/LICENSE
brushit-0.3.0.dist-info/METADATA
brushit-0.3.0.dist-info/WHEEL
brushit-0.3.0.dist-info/entry_points.txt
brushit-0.3.0.dist-info/RECORD
