Metadata-Version: 2.1
Name: brushit
Version: 0.3.0
Summary: 
Requires-Python: >=3.10,<4.0
Classifier: Programming Language :: Python :: 3
Classifier: Programming Language :: Python :: 3.10
Classifier: Programming Language :: Python :: 3.11
Classifier: Programming Language :: Python :: 3.12
Requires-Dist: clipstick (>=0.3.5,<0.4.0)
Requires-Dist: questionary (==2.0.0)
